wseg/__init__.py
wseg/dict_based.py
wseg/hmm.py
wseg/__pycache__/__init__.cpython-36.pyc
wseg/__pycache__/dict_based.cpython-36.pyc
wseg/__pycache__/hmm.cpython-36.pyc
wseg/libs/BIMM.cp36-win_amd64.pyd
wseg/libs/HMM.cp36-win_amd64.pyd
wseg-0.0.1a3.dist-info/LICENSE.txt
wseg-0.0.1a3.dist-info/METADATA
wseg-0.0.1a3.dist-info/WHEEL
wseg-0.0.1a3.dist-info/top_level.txt
wseg-0.0.1a3.dist-info/RECORD
